ibapiplus/__init__.py
ibapiplus/client.py
ibapiplus-0.1.4.dist-info/METADATA
ibapiplus-0.1.4.dist-info/WHEEL
ibapiplus-0.1.4.dist-info/top_level.txt
ibapiplus-0.1.4.dist-info/RECORD
